qitip/__init__.py
qitip/__main__.py
qitip/main.py
qitip/prover.py
qitip/qitip.py
qitip/quantum_inequalities.py
qitip/objects/__init__.py
qitip/objects/constraints.py
qitip/objects/entrospace.py
qitip/objects/inequality.py
qitip/objects/type_result.py
qitip/objects/typings.py
qitip/utils/__init__.py
qitip/utils/converters.py
qitip/utils/validators.py
qitip-0.1.1.dist-info/LICENSE
qitip-0.1.1.dist-info/METADATA
qitip-0.1.1.dist-info/WHEEL
qitip-0.1.1.dist-info/top_level.txt
qitip-0.1.1.dist-info/RECORD
