Metadata-Version: 2.1
Name: qitip
Version: 0.1.1
Summary: Python package that serves as quantum information inequality prover
Author-email: Shao-Lun Huang <shaolh105022105@gmail.com>
License: MIT
Project-URL: Home, https://github.com/Jamespark0/qitip
Requires-Python: >=3.11
License-File: LICENSE
Requires-Dist: numpy >=1.26.4
Requires-Dist: scipy >=1.12.0
